{
    "DIM_UI_MENU_BAR": {
      "HEIGHT_FRACTION": 0.05,
      "BUTTON_WIDTH_ABSOLUTE": 200,
      "BUTTON_PAD_ABSOLUTE": 5
    },
    "DIM_UI_LAYOUT2": {
      "LEFT_WIDTH_FRACTION": 0.15,
      "MIDDLE_WIDTH_FRACTION": 0.5,
      "RIGHT_WIDTH_FRACTION": 0.35,
      "LEFT_BUTTON_PAD_ABSOLUTE": 10,
      "LEFT_BUTTON_HEIGHT_ABSOLUTE": 50,
      "MID_MENU_WIDTH_ABSOLUTE": 200,
      "MID_MENU_HEIGTH_ABSOLUTE": 50,
      "BUTTONS_HEIGHT_ABSOLUTE": 35,
      "TREEVIEW_HEIGHT_ABSOLUTE": 500,
      "RIGHT_PAD_ABSOLUTE": 10
    },
    "DIM_UI_LAYOUT3": {
      "LEFT_WIDTH_FRACTION": 0.1,
      "MIDDLE_WIDTH_FRACTION": 0.5,
      "RIGHT_WIDTH_FRACTION": 0.4,
      "MIDDLE_SPLIT1_FRACTION": 0.45,
      "MIDDLE_SPLIT2_FRACTION": 0.1,
      "MIDDLE_SPLIT3_FRACTION": 0.45,
      "PRODUCT_IMAGE_SIZE_ABSOLUTE": 350,
      "LEFT_PADY_ABSOLUTE": 5,
      "LEFT_HEIGHT_ABSOLUTE": 60
    },
    "DIM_UI_MOVEMENT_ANIMATION": {
      "ANIMATION_SPEED": 0.2,
      "ANIMATION_STEPS": 200
    }
  }
